roboutils/__init__.py
roboutils/roboutils.py
robo_utils-0.2.7.dist-info/LICENSE
robo_utils-0.2.7.dist-info/METADATA
robo_utils-0.2.7.dist-info/WHEEL
robo_utils-0.2.7.dist-info/top_level.txt
robo_utils-0.2.7.dist-info/RECORD
