Metadata-Version: 2.1
Name: robo-utils
Version: 0.2.7
Summary: Useful functions for mobile robotics
Home-page: https://github.com/mkner/robo-utils
Author: Mike Knerr
License: BSD
Keywords: robotics,mobile robotics,utilities,numeric bounding,sensor ranging,trigonmetric conversion,toolkit
Platform: UNKNOWN
Classifier: Programming Language :: Python :: 3
Classifier: License :: OSI Approved :: BSD License
Classifier: Operating System :: OS Independent
License-File: LICENSE
